odoo/addons/login_user_detail/__init__.py
odoo/addons/login_user_detail/__manifest__.py
odoo/addons/login_user_detail/models/__init__.py
odoo/addons/login_user_detail/models/login_user_details.py
odoo/addons/login_user_detail/security/ir.model.access.csv
odoo/addons/login_user_detail/views/login_user_views.xml
odoo12_addon_login_user_detail-12.0.1.0.3.dist-info/METADATA
odoo12_addon_login_user_detail-12.0.1.0.3.dist-info/WHEEL
odoo12_addon_login_user_detail-12.0.1.0.3.dist-info/top_level.txt
odoo12_addon_login_user_detail-12.0.1.0.3.dist-info/RECORD
