Metadata-Version: 2.1
Name: odoo12-addon-login-user-detail
Version: 12.0.1.0.3
Summary: Login User Details & IP Address
Home-page: https://www.cybrosys.com
Author: Cybrosys Techno Solutions
License: LGPL-3
Platform: UNKNOWN
Classifier: Programming Language :: Python
Classifier: Framework :: Odoo
Classifier: License :: OSI Approved :: GNU Lesser General Public License v3 (LGPLv3)
Requires-Python: >=3.5
Requires-Dist: odoo12-addon-auth-oidc
Requires-Dist: odoo (<12.1dev,>=12.0a)
